httpx_cli/__init__.py
httpx_cli/_cli.py
httpx_cli/_help.py
httpx_cli/_utils.py
httpx_cli-0.1.2.dist-info/METADATA
httpx_cli-0.1.2.dist-info/WHEEL
httpx_cli-0.1.2.dist-info/entry_points.txt
httpx_cli-0.1.2.dist-info/top_level.txt
httpx_cli-0.1.2.dist-info/RECORD
